{"metadata":{"asset_id":"2fb45c27-50a3-4dbe-82f5-4ec54e54c429","asset_attributes":["data_asset"],"name":"example.json","asset_type":"data_asset","created_at":"2021-06-01T15:17:51Z","description":"","origin_country":"us","owner_id":"1000331005","project_id":"810bc6b8-87ae-4991-a3af-673d301f7895","size":154,"tags":[],"usage":{"last_update_time":1622560674333,"last_updated_at":"2021-06-01T15:17:54Z"}},"entity":{"data_asset":{"mime_type":"application/json","dataset":false}},"attachments":[{"id":"64ec7f2e-cd75-4712-a9c9-cb0c5e321a6c","version":2,"asset_type":"data_asset","name":"example.json","mime":"application/json","datasource_type":"81bafdbd-b7c6-45c5-a4fd-6ec135f66f4e","object_key":"data_asset/example.json","creator_id":"1000331005","create_time":1622560674333,"size":154,"is_remote":false,"is_managed":false,"is_referenced":true,"is_object_key_read_only":true,"is_user_provided_path_key":true,"transfer_complete":true,"is_partitioned":false,"complete_time_ticks":1622560674333,"user_data":{},"test_doc":0,"handle":{"key":"data_asset/example.json","upload_id":"done","max_part_num":1},"usage":{"access_count":0,"last_accessor_id":"1000331005","last_access_time":1622560674333}}]}